<?xml version="1.0" encoding="UTF-8" standalone="yes"?>
<sst xmlns="http://schemas.openxmlformats.org/spreadsheetml/2006/main" count="142" uniqueCount="26"><si><t>Start Date</t></si><si><t>Start Time</t></si><si><t>End Date</t></si><si><t>End Time</t></si><si><t>Location</t></si><si><t>Distance</t></si><si><t>Duration</t></si><si><t>Average Speed</t></si><si><t>Month</t></si><si><t>Distance Rounded</t></si><si><t>Ghent</t></si><si><t>Schulen</t></si><si><t>Brussels</t></si><si><t>Lummen</t></si><si><t>Antwerp</t></si><si><t>Heusden-Zolder</t></si><si><t>Values</t></si><si><t>Row Labels</t></si><si><t>Speed</t></si><si><t>Grand Total</t></si><si><t>(All)</t></si><si><t>01</t></si><si><t>02</t></si><si><t>03</t></si><si><t>04</t></si><si><t>05</t></si></sst>